ipos/__init__.py
ipos/_modidx.py
ipos/gimp.py
ipos/imp.py
ipos/types.py
ipos/utils.py
ipos-0.0.16.dist-info/LICENSE
ipos-0.0.16.dist-info/METADATA
ipos-0.0.16.dist-info/WHEEL
ipos-0.0.16.dist-info/entry_points.txt
ipos-0.0.16.dist-info/top_level.txt
ipos-0.0.16.dist-info/RECORD
